MANIFEST.in
README
requirements.txt
setup.py
ajenti.plugin.filesystem.egg-info/PKG-INFO
ajenti.plugin.filesystem.egg-info/SOURCES.txt
ajenti.plugin.filesystem.egg-info/dependency_links.txt
ajenti.plugin.filesystem.egg-info/requires.txt
ajenti.plugin.filesystem.egg-info/top_level.txt
ajenti_plugin_filesystem/README.md
ajenti_plugin_filesystem/__init__.py
ajenti_plugin_filesystem/bower.json
ajenti_plugin_filesystem/main.py
ajenti_plugin_filesystem/plugin.yml
ajenti_plugin_filesystem/requirements.txt
ajenti_plugin_filesystem/tasks.py
ajenti_plugin_filesystem/views.py
ajenti_plugin_filesystem/widget.py
ajenti_plugin_filesystem/locale/app.pot
ajenti_plugin_filesystem/locale/af/LC_MESSAGES/app.js
ajenti_plugin_filesystem/locale/af/LC_MESSAGES/app.po
ajenti_plugin_filesystem/locale/af/LC_MESSAGES/app.po~
ajenti_plugin_filesystem/locale/ar/LC_MESSAGES/app.js
ajenti_plugin_filesystem/locale/ar/LC_MESSAGES/app.po
ajenti_plugin_filesystem/locale/ar/LC_MESSAGES/app.po~
ajenti_plugin_filesystem/locale/be/LC_MESSAGES/app.js
ajenti_plugin_filesystem/locale/be/LC_MESSAGES/app.po
ajenti_plugin_filesystem/locale/be/LC_MESSAGES/app.po~
ajenti_plugin_filesystem/locale/bg/LC_MESSAGES/app.js
ajenti_plugin_filesystem/locale/bg/LC_MESSAGES/app.po
ajenti_plugin_filesystem/locale/bg/LC_MESSAGES/app.po~
ajenti_plugin_filesystem/locale/bn/LC_MESSAGES/app.js
ajenti_plugin_filesystem/locale/bn/LC_MESSAGES/app.po
ajenti_plugin_filesystem/locale/bn/LC_MESSAGES/app.po~
ajenti_plugin_filesystem/locale/bs/LC_MESSAGES/app.js
ajenti_plugin_filesystem/locale/bs/LC_MESSAGES/app.po
ajenti_plugin_filesystem/locale/ca/LC_MESSAGES/app.js
ajenti_plugin_filesystem/locale/ca/LC_MESSAGES/app.po
ajenti_plugin_filesystem/locale/ca/LC_MESSAGES/app.po~
ajenti_plugin_filesystem/locale/cs/LC_MESSAGES/app.js
ajenti_plugin_filesystem/locale/cs/LC_MESSAGES/app.po
ajenti_plugin_filesystem/locale/cs/LC_MESSAGES/app.po~
ajenti_plugin_filesystem/locale/da/LC_MESSAGES/app.js
ajenti_plugin_filesystem/locale/da/LC_MESSAGES/app.po
ajenti_plugin_filesystem/locale/da/LC_MESSAGES/app.po~
ajenti_plugin_filesystem/locale/de/LC_MESSAGES/app.js
ajenti_plugin_filesystem/locale/de/LC_MESSAGES/app.po
ajenti_plugin_filesystem/locale/de/LC_MESSAGES/app.po~
